comms_utils/__init__.py
comms_utils/ak.py
comms_utils/comb.py
comms_utils/decode.py
comms_utils/encode.py
comms_utils/plot.py
comms_utils/psd.py
comms_utils/pulse.py
comms_utils/rn.py
comms_utils/signal.py
comms_utils/threaded.py
comms_utils-1.0.0.dist-info/LICENCE
comms_utils-1.0.0.dist-info/METADATA
comms_utils-1.0.0.dist-info/WHEEL
comms_utils-1.0.0.dist-info/top_level.txt
comms_utils-1.0.0.dist-info/RECORD
