Metadata-Version: 2.1
Name: comms-utils
Version: 1.0.0
Summary: A set of tools for the ENEL422 Comms Assignment
Home-page: https://github.com/JosiahCraw/Python-Comms-Utils-ENEL422-
Author: Jos Craw
Author-email: jos@joscraw.net
License: UNKNOWN
Platform: UNKNOWN
Classifier: Programming Language :: Python :: 3
Classifier: License :: OSI Approved :: MIT License
Classifier: Operating System :: OS Independent
Requires-Python: >=3.6
